core.py
queryable_list-1.0.5.dist-info/LICENSE
queryable_list-1.0.5.dist-info/METADATA
queryable_list-1.0.5.dist-info/WHEEL
queryable_list-1.0.5.dist-info/top_level.txt
queryable_list-1.0.5.dist-info/RECORD
