Metadata-Version: 2.1
Name: queryable-list
Version: 1.0.5
Summary: Forget classical list filtering and enjoy yourself by generating flexible and fluent list queries with QueryableList.
Home-page: https://github.com/cinarizasyon/python-queryable-list
Author: cinarizasyon
Author-email: cancinar57@gmail.com
License: UNKNOWN
Platform: UNKNOWN
Classifier: Programming Language :: Python :: 2.7
Classifier: Programming Language :: Python :: 3.5
Classifier: Programming Language :: Python :: 3.6
Classifier: Programming Language :: Python :: 3.7
Classifier: Programming Language :: Python :: 3.8
Classifier: Programming Language :: Python :: 3.9
Classifier: License :: OSI Approved :: MIT License
Classifier: Operating System :: OS Independent
Requires-Python: >=2.7
Requires-Dist: six (==1.15)
Provides-Extra: dev
Requires-Dist: mock (==3.0.5) ; extra == 'dev'
